{
  "schema_version": "1.0",
  "bundle_kind": "kaos-compliance.package",
  "package": "kaos-web",
  "version": "0.1.0a2",
  "snapshot_slice": {
    "name": "kaos-web",
    "identity": {
      "pypi_version": "0.1.0a2",
      "pypi_url": "https://pypi.org/project/kaos-web/0.1.0a2/",
      "main_head_sha": "7d210cc8be8466b99b454f26a5a2b680c22ab74c",
      "latest_tag": "v0.1.0a2",
      "latest_tag_sha": "9d9756fab60bdec4acde1658d0253b1d6b51e511",
      "tag_at_head": false,
      "commits_past_tag": null,
      "repo_visibility": "public",
      "last_commit_at": "2026-05-14T01:08:36Z"
    },
    "ci": {
      "workflow_conclusion": "success",
      "workflow_run_id": 25835616058,
      "workflow_run_url": "https://github.com/273v/kaos-web/actions/runs/25835616058",
      "head_sha": "7d210cc8be8466b99b454f26a5a2b680c22ab74c",
      "run_completed_at": "2026-05-14T01:14:08Z",
      "matrix": [
        {
          "name": "Test against minimum dependencies",
          "conclusion": "success",
          "status": "completed",
          "started_at": "2026-05-14T01:10:03Z",
          "completed_at": "2026-05-14T01:11:08Z",
          "duration_seconds": 65
        },
        {
          "name": "Test (linux-x64 / Python 3.14t)",
          "conclusion": "success",
          "status": "completed",
          "started_at": "2026-05-14T01:11:36Z",
          "completed_at": "2026-05-14T01:13:11Z",
          "duration_seconds": 95
        },
        {
          "name": "Test (linux-x64 / Python 3.14)",
          "conclusion": "success",
          "status": "completed",
          "started_at": "2026-05-14T01:11:18Z",
          "completed_at": "2026-05-14T01:12:39Z",
          "duration_seconds": 81
        },
        {
          "name": "Lint",
          "conclusion": "success",
          "status": "completed",
          "started_at": "2026-05-14T01:12:08Z",
          "completed_at": "2026-05-14T01:12:21Z",
          "duration_seconds": 13
        },
        {
          "name": "Pre-commit hooks",
          "conclusion": "success",
          "status": "completed",
          "started_at": "2026-05-14T01:08:49Z",
          "completed_at": "2026-05-14T01:09:10Z",
          "duration_seconds": 21
        },
        {
          "name": "Test (linux-x64 / Python 3.13)",
          "conclusion": "success",
          "status": "completed",
          "started_at": "2026-05-14T01:11:39Z",
          "completed_at": "2026-05-14T01:13:31Z",
          "duration_seconds": 112
        },
        {
          "name": "Test (linux-x64 / Python 3.15)",
          "conclusion": "success",
          "status": "completed",
          "started_at": "2026-05-14T01:13:09Z",
          "completed_at": "2026-05-14T01:13:47Z",
          "duration_seconds": 38
        },
        {
          "name": "Test (windows-x64 / Python 3.13)",
          "conclusion": "success",
          "status": "completed",
          "started_at": "2026-05-14T01:08:42Z",
          "completed_at": "2026-05-14T01:11:18Z",
          "duration_seconds": 156
        },
        {
          "name": "Test (macos-arm64 / Python 3.13)",
          "conclusion": "success",
          "status": "completed",
          "started_at": "2026-05-14T01:08:42Z",
          "completed_at": "2026-05-14T01:10:10Z",
          "duration_seconds": 88
        },
        {
          "name": "Build distribution + smoke test",
          "conclusion": "success",
          "status": "completed",
          "started_at": "2026-05-14T01:13:50Z",
          "completed_at": "2026-05-14T01:14:08Z",
          "duration_seconds": 18
        }
      ]
    },
    "security": {
      "workflow_conclusion": "success",
      "workflow_run_id": 25835616052,
      "workflow_run_url": "https://github.com/273v/kaos-web/actions/runs/25835616052",
      "jobs": [
        {
          "name": "vulture (dead-code scan)",
          "conclusion": "success",
          "status": "completed",
          "completed_at": "2026-05-14T01:08:58Z"
        },
        {
          "name": "gitleaks (secret scan)",
          "conclusion": "success",
          "status": "completed",
          "completed_at": "2026-05-14T01:08:47Z"
        },
        {
          "name": "bandit (static security)",
          "conclusion": "success",
          "status": "completed",
          "completed_at": "2026-05-14T01:08:55Z"
        },
        {
          "name": "pip-audit (dependency CVEs)",
          "conclusion": "success",
          "status": "completed",
          "completed_at": "2026-05-14T01:09:07Z"
        }
      ],
      "run_completed_at": "2026-05-14T01:09:08Z"
    },
    "open_prs": {
      "count": 5,
      "titles": [
        "#14 chore(deps-dev): bump kaos-mcp from 0.1.0a2 to 0.1.0a3",
        "#13 chore(deps): bump kaos-content from 0.1.0a4 to 0.1.0a6",
        "#12 chore(deps-dev): bump kaos-nlp-core from 0.1.0a2 to 0.1.0a3",
        "#11 chore(deps): bump kaos-core from 0.1.0a5 to 0.1.0a6",
        "#10 chore(deps): bump the actions-all group with 4 updates"
      ]
    },
    "freshness": {
      "days_since_last_commit": 0,
      "days_since_last_release": 3,
      "days_since_last_security_scan": 0
    },
    "supply_chain": {
      "pypi_version": "0.1.0a2",
      "pypi_release_iso": "2026-05-11T01:35:01.893176Z",
      "wheel_platforms": [
        "any"
      ],
      "wheel_sha256s": {
        "kaos_web-0.1.0a2-py3-none-any.whl": "de0f8fb6c615c4f1c1b01db40dd6fa7536102f45c7e19f7f77da87b573d90b94",
        "kaos_web-0.1.0a2.tar.gz": "8b55fa64cdcf534c82ce13e2e4247ffc100730b7a260aa66add37329238be588"
      },
      "is_abi3": false,
      "has_musllinux_wheel": false,
      "license_expression": "Apache-2.0",
      "license_files_in_wheel": [
        "LICENSE",
        "NOTICE"
      ],
      "attestations": {
        "pep740_present": true,
        "publisher_kind": "GitHub",
        "publisher_source_repo": "273v/kaos-web",
        "publisher_workflow_ref": "release.yml@pypi",
        "rekor_log_index": 1501277327,
        "verified_count": 2,
        "total_count": 2
      },
      "sbom": {
        "components_count": 64,
        "license_breakdown": {
          "MIT": 35,
          "MPL-2.0": 1,
          "BSD-3-Clause": 11,
          "Apache-2.0": 7,
          "Apache-2.0 OR BSD-3-Clause": 1,
          "ISC": 2,
          "MIT AND PSF-2.0": 1,
          "Apache-2.0 OR BSD-2-Clause": 1,
          "LicenseRef-unknown-e3b0c442": 1,
          "BSD-2-Clause": 2,
          "Python-2.0": 1,
          "PSF-2.0": 1
        },
        "weak_copyleft": [
          "certifi"
        ],
        "strong_copyleft": [],
        "unknown_license": [
          "playwright"
        ],
        "sbom_artifact_path": "data/sbom/kaos-web-0.1.0a2.cdx.json"
      },
      "errors": []
    },
    "governance": {
      "dco_signoff_rate_90d": 0.07,
      "conventional_commits_rate_90d": 0.413,
      "verified_commit_ratio_90d": 0.07,
      "commits_90d": 143,
      "unique_committers_90d": 1,
      "branch_protection_enabled": true,
      "branch_protection_summary": {
        "source": "branches_api",
        "required_status_checks": {
          "enforcement_level": "everyone",
          "contexts": [
            "Lint",
            "Pre-commit hooks",
            "Test (linux-x64 / Python 3.13)",
            "Test (linux-x64 / Python 3.14)",
            "Test against minimum dependencies",
            "Build distribution + smoke test",
            "gitleaks (secret scan)",
            "pip-audit (dependency CVEs)",
            "bandit (static security)",
            "vulture (dead-code scan)"
          ],
          "checks": [
            {
              "context": "Lint",
              "app_id": 15368
            },
            {
              "context": "Pre-commit hooks",
              "app_id": 15368
            },
            {
              "context": "Test (linux-x64 / Python 3.13)",
              "app_id": 15368
            },
            {
              "context": "Test (linux-x64 / Python 3.14)",
              "app_id": 15368
            },
            {
              "context": "Test against minimum dependencies",
              "app_id": 15368
            },
            {
              "context": "Build distribution + smoke test",
              "app_id": 15368
            },
            {
              "context": "gitleaks (secret scan)",
              "app_id": 15368
            },
            {
              "context": "pip-audit (dependency CVEs)",
              "app_id": 15368
            },
            {
              "context": "bandit (static security)",
              "app_id": 15368
            },
            {
              "context": "vulture (dead-code scan)",
              "app_id": 15368
            }
          ]
        },
        "required_pull_request_reviews": null,
        "required_signatures": null
      },
      "codeowners_path": ".github/CODEOWNERS",
      "security_md_present": true,
      "security_md_disclosure_window_days": 90,
      "notice_present": true,
      "license_files_in_sdist": [
        "LICENSE",
        "NOTICE"
      ],
      "releases_90d": 2,
      "median_pr_age_days": 1.801,
      "open_pr_count": 5,
      "open_issue_count": 0,
      "time_to_pypi_seconds_median": 162,
      "errors": []
    },
    "code_metrics": {
      "python": {
        "src_loc": 12389,
        "tests_loc": 13308,
        "src_files": 61,
        "tests_files": 59
      },
      "rust": {
        "src_loc": 0,
        "tests_loc": 0,
        "src_files": 0,
        "tests_files": 0
      },
      "errors": []
    },
    "errors": []
  },
  "sbom": {
    "mirror_path": "api/v1/sbom/kaos-web-0.1.0a2.cdx.json",
    "github_release_url": "https://github.com/273v/kaos-web/releases/download/v0.1.0a2/kaos-web-0.1.0a2.cdx.json"
  },
  "attestation": {
    "present": true,
    "publisher_kind": "GitHub",
    "publisher_source_repo": "273v/kaos-web",
    "publisher_workflow_ref": "release.yml@pypi",
    "rekor_log_index": 1501277327,
    "verified_count": 2,
    "total_count": 2,
    "pypi_simple_index_url": "https://pypi.org/simple/kaos-web/"
  }
}
